readwise_mcp/__init__.py
readwise_mcp/tools/readwise/common.py
readwise_mcp/tools/readwise/get_document.py
readwise_mcp/tools/readwise/get_highlights.py
readwise_mcp/types/book.py
readwise_mcp/types/highlight.py
readwise_mcp/types/tag.py
readwise_mcp/utils/__init__.py
readwise_mcp/utils/duration.py
iflow_mcp_kiseki_labs_readwise_mcp-0.1.0.dist-info/METADATA
iflow_mcp_kiseki_labs_readwise_mcp-0.1.0.dist-info/WHEEL
iflow_mcp_kiseki_labs_readwise_mcp-0.1.0.dist-info/top_level.txt
iflow_mcp_kiseki_labs_readwise_mcp-0.1.0.dist-info/RECORD
