Metadata-Version: 2.4
Name: iflow-mcp_kiseki-labs-readwise-mcp
Version: 0.1.0
Summary: MCP Server for Readwise
Requires-Python: >=3.10.0
Requires-Dist: fastmcp>=2.2.0
Requires-Dist: httpx>=0.28.1
